AUTHORS
MANIFEST.in
setup.py
django_crud/__init__.py
django_crud/models.py
django_crud/tests.py
django_crud/urls.py
django_crud/views.py
django_crud.egg-info/PKG-INFO
django_crud.egg-info/SOURCES.txt
django_crud.egg-info/dependency_links.txt
django_crud.egg-info/not-zip-safe
django_crud.egg-info/top_level.txt