Metadata-Version: 1.0
Name: django-crud
Version: 0.12
Summary: CRUD application for Django
Home-page: http://github.com/darvin/django-crud/
Author: Sergey Klimov
Author-email: sergey.v.klimov@gmail.com
License: UNKNOWN
Platform: UNKNOWN
Classifier: Development Status :: 3 - Alpha
Classifier: Environment :: Web Environment
Classifier: Intended Audience :: Developers
Classifier: License :: OSI Approved :: BSD License
Classifier: Operating System :: OS Independent
Classifier: Programming Language :: Python
Classifier: Framework :: Django
